Compiled from "JvmTest.java"
public class com.hp.learn.base.JvmTest {
  public com.hp.learn.base.JvmTest();
    Code:
       0: aload_0
       1: invokespecial #1                  // Method java/lang/Object."<init>":()V
       4: return

  public static void main(java.lang.String[]);
    Code:
       0: ldc           #2                  // int 103831
       2: istore_1
       3: ldc           #3                  // int 123242412
       5: istore_2
       6: iload_1
       7: iload_2
       8: invokestatic  #4                  // Method computer:(II)I
      11: istore_3
      12: new           #5                  // class com/hp/learn/base/JvmTest
      15: dup
      16: invokespecial #6                  // Method "<init>":()V
      19: astore        4
      21: aload         4
      23: iload_1
      24: iload_2
      25: invokevirtual #7                  // Method compter2:(II)I
      28: istore        5
      30: ldc           #8                  // String abcdefg
      32: astore        6
      34: return

  public static int computer(int, int);
    Code:
       0: iload_0
       1: iload_1
       2: iconst_2
       3: iadd
       4: imul
       5: dup
       6: istore_0
       7: ireturn

  public int compter2(int, int);
    Code:
       0: iload_1
       1: iload_2
       2: iadd
       3: ireturn
}
